offsettmpsubs/__init__.py
offsettmpsubs/__main__.py
offsettmpsubs/offsettmpsubs.py
offsettmpsubs-1.0.0.dist-info/LICENSE
offsettmpsubs-1.0.0.dist-info/METADATA
offsettmpsubs-1.0.0.dist-info/WHEEL
offsettmpsubs-1.0.0.dist-info/entry_points.txt
offsettmpsubs-1.0.0.dist-info/top_level.txt
offsettmpsubs-1.0.0.dist-info/RECORD
