Metadata-Version: 2.1
Name: offsettmpsubs
Version: 1.0.0
Summary: A cli tool for delaying/hastening subtitles in stored in TMP format.
Home-page: https://github.com/luciferDisciple/offsettmpsubs
Author: Piotr Momot
Author-email: waizer12@gmail.com
License: MIT License
Classifier: License :: OSI Approved :: MIT License
Classifier: Operating System :: OS Independent
Classifier: Programming Language :: Python :: 3
Requires-Python: >=3.8
License-File: LICENSE
